{"trial_id": "0147", "hyperparameters": {"space": [{"class_name": "Int", "config": {"name": "units", "default": null, "conditions": [], "min_value": 32, "max_value": 512, "step": 32, "sampling": "linear"}}, {"class_name": "Float", "config": {"name": "l1", "default": 1e-06, "conditions": [], "min_value": 1e-06, "max_value": 0.01, "step": null, "sampling": "log"}}, {"class_name": "Float", "config": {"name": "l2", "default": 1e-06, "conditions": [], "min_value": 1e-06, "max_value": 0.01, "step": null, "sampling": "log"}}, {"class_name": "Float", "config": {"name": "dropout", "default": 0.0, "conditions": [], "min_value": 0.0, "max_value": 0.5, "step": 0.1, "sampling": "linear"}}, {"class_name": "Float", "config": {"name": "learning_rate", "default": 0.0001, "conditions": [], "min_value": 0.0001, "max_value": 0.01, "step": null, "sampling": "log"}}], "values": {"units": 448, "l1": 4.803963853535188e-05, "l2": 0.0009655252832573445, "dropout": 0.1, "learning_rate": 0.001991490896520728, "tuner/epochs": 100, "tuner/initial_epoch": 34, "tuner/bracket": 4, "tuner/round": 4, "tuner/trial_id": "0145"}}, "metrics": {"metrics": {"accuracy": {"direction": "max", "observations": [{"value": [0.8183469772338867], "step": 9}]}, "loss": {"direction": "min", "observations": [{"value": [0.6424434781074524], "step": 9}]}, "val_accuracy": {"direction": "max", "observations": [{"value": [0.7956403493881226], "step": 9}]}, "val_loss": {"direction": "min", "observations": [{"value": [0.8309503197669983], "step": 9}]}}}, "score": 0.7956403493881226, "best_step": 9, "status": "COMPLETED", "message": null}